oneclick_context/__init__.py
oneclick_context/cli.py
oneclick_context/commands/generate.py
oneclick_context/core.py
oneclick_context/exporters/__init__.py
oneclick_context/exporters/html.py
oneclick_context/exporters/json.py
oneclick_context/exporters/markdown.py
oneclick_context/exporters/text.py
oneclick_context/prompts.py
oneclick_context/utils.py
oneclick_context-0.2.2.dist-info/METADATA
oneclick_context-0.2.2.dist-info/WHEEL
oneclick_context-0.2.2.dist-info/entry_points.txt
oneclick_context-0.2.2.dist-info/RECORD
