Metadata-Version: 2.3
Name: oneclick-context
Version: 0.2.2
Summary: One-Click Context Toolkit - visual file trees + AI summaries
Author: frost
Author-email: lucasthelearner@gmail.com
Requires-Python: >=3.10,<4.0
Classifier: Programming Language :: Python :: 3
Classifier: Programming Language :: Python :: 3.10
Classifier: Programming Language :: Python :: 3.11
Classifier: Programming Language :: Python :: 3.12
Classifier: Programming Language :: Python :: 3.13
Requires-Dist: anytree (>=2.12,<3.0)
Requires-Dist: click (>=8.1,<9)
Requires-Dist: questionary (>=2.1.0,<3.0.0)
Requires-Dist: rich (>=13.7,<14.0)
Requires-Dist: typer (>=0.12.3,<0.13.0)
